fusebase/__init__.py
FuseBase-0.0.5.dist-info/LICENSE
FuseBase-0.0.5.dist-info/METADATA
FuseBase-0.0.5.dist-info/WHEEL
FuseBase-0.0.5.dist-info/top_level.txt
FuseBase-0.0.5.dist-info/zip-safe
FuseBase-0.0.5.dist-info/RECORD
