Metadata-Version: 2.1
Name: FuseBase
Version: 0.0.5
Summary: Just some primitives for implementing a FUSE filesystem.
Home-page: https://alexdelorenzo.dev
Author: Alex DeLorenzo
License: AGPL-3.0
Keywords: fuse
Platform: UNKNOWN
Requires-Python: ~=3.7
